PyShorts/__init__.py
PyShorts/funcs.py
PyShorts/non_use_funcs.py
PyShorts/Sub_Functions/__init__.py
PyShorts/Sub_Functions/funcs.py
PyShorts/Sub_Functions/non_use_funcs.py
sampackage/__init__.py
sampackage/funcs.py
sampackage/non_use_funcs.py
Sampackage-0.7.dist-info/METADATA
Sampackage-0.7.dist-info/WHEEL
Sampackage-0.7.dist-info/top_level.txt
Sampackage-0.7.dist-info/RECORD
